excel_mcp/__main__.py
excel_mcp/calculations.py
excel_mcp/cell_utils.py
excel_mcp/cell_validation.py
excel_mcp/chart.py
excel_mcp/data.py
excel_mcp/exceptions.py
excel_mcp/formatting.py
excel_mcp/pivot.py
excel_mcp/server.py
excel_mcp/sheet.py
excel_mcp/tables.py
excel_mcp/toon_utils.py
excel_mcp/validation.py
excel_mcp/workbook.py
excel_mcp_toon-0.1.9.dist-info/licenses/LICENSE
excel_mcp_toon-0.1.9.dist-info/METADATA
excel_mcp_toon-0.1.9.dist-info/WHEEL
excel_mcp_toon-0.1.9.dist-info/entry_points.txt
excel_mcp_toon-0.1.9.dist-info/top_level.txt
excel_mcp_toon-0.1.9.dist-info/RECORD
