Metadata-Version: 2.4
Name: excel-mcp-toon
Version: 0.1.9
Summary: Excel MCP Server for manipulating Excel files
Author-email: haris <haris.musa@outlook.com>
Requires-Python: >=3.10
License-File: LICENSE
Requires-Dist: mcp[cli]>=1.10.1
Requires-Dist: fastmcp<3.0.0,>=2.0.0
Requires-Dist: openpyxl>=3.1.5
Requires-Dist: typer>=0.16.0
Requires-Dist: toon-format>=0.1.0
Dynamic: license-file
